README.md
setup.py
qinglan/__init__.py
qinglan/cmd.py
qinglan/helloworld.py
qinglan.egg-info/PKG-INFO
qinglan.egg-info/SOURCES.txt
qinglan.egg-info/dependency_links.txt
qinglan.egg-info/entry_points.txt
qinglan.egg-info/top_level.txt