Metadata-Version: 2.1
Name: qinglan
Version: 0.0.3
Summary: This is a scaffold for nicegui,just like ruby on rails
Author: thekingofhero
Author-email: thekingofhero@live.com
License: MIT
